httpx_sse/__init__.py
httpx_sse/_api.py
httpx_sse/_decoders.py
httpx_sse/_exceptions.py
httpx_sse/_models.py
httpx_sse/py.typed
httpx_sse-0.3.0.dist-info/LICENSE
httpx_sse-0.3.0.dist-info/METADATA
httpx_sse-0.3.0.dist-info/WHEEL
httpx_sse-0.3.0.dist-info/top_level.txt
httpx_sse-0.3.0.dist-info/RECORD
