Metadata-Version: 2.1
Name: httpx-sse
Version: 0.3.0
Summary: Consume Server-Sent Event (SSE) messages with HTTPX.
Author-email: Florimond Manca <florimond.manca@protonmail.com>
License: MIT
Project-URL: Homepage, https://github.com/florimondmanca/httpx-sse
Classifier: Development Status :: 4 - Beta
Classifier: Intended Audience :: Developers
Classifier: Programming Language :: Python :: 3
Classifier: Programming Language :: Python :: 3 :: Only
Classifier: Programming Language :: Python :: 3.7
Classifier: Programming Language :: Python :: 3.8
Classifier: Programming Language :: Python :: 3.9
Classifier: Programming Language :: Python :: 3.10
Classifier: Programming Language :: Python :: 3.11
Requires-Python: >=3.7
License-File: LICENSE
